{
    "all": {
        "10": [
            {
                "name": "Forgotten Outpost",
                "type": "region"
            }
        ]
    },
    "warrior":{
        "0": [
            {
                "id": "slash",
                "name": "Slash",
                "type": "ability"
            }
        ],
        "4": [
            {
                "id": "bite",
                "name": "Bite",
                "type": "ability"
            }
        ]
    },
    "assassin":{
        "0": [
            {
                "id": "slash",
                "type": "ability"
            }
        ]
    },
    "magician":{
        "0": [
            {
                "id": "slash",
                "type": "ability"
            }
        ]
    },
    "ranger":{
        "0": [
            {
                "id": "slash",
                "type": "ability"
            }
        ]
    },
    "healer":{
        "0": [
            {
                "id": "slash",
                "type": "ability"
            }
        ]
    }
}